shaftaloo/__init__.py
shaftaloo/runner.py
shaftaloo-0.0.2.dist-info/METADATA
shaftaloo-0.0.2.dist-info/WHEEL
shaftaloo-0.0.2.dist-info/top_level.txt
shaftaloo-0.0.2.dist-info/RECORD
