Metadata-Version: 2.1
Name: shaftaloo
Version: 0.0.2
Summary: An open-source python package
Home-page: https://github.com/mohammadamint/shaftaloo/
License: European Union Public License 1.2
Requires-Python: >=3.6.0
Requires-Dist: pandas (>=1.3.3)
Requires-Dist: numpy (>=1.21.2)
Requires-Dist: xlsxwriter (>=1.3.7)
Requires-Dist: matplotlib (>=3.3.4)
Requires-Dist: openpyxl (>=3.0.6)
Requires-Dist: tqdm
